dictionary/__init__.py
dictionary/dictionary.py
kamil_kaan_erkan_dictionary_1-2.0.0.dist-info/METADATA
kamil_kaan_erkan_dictionary_1-2.0.0.dist-info/WHEEL
kamil_kaan_erkan_dictionary_1-2.0.0.dist-info/top_level.txt
kamil_kaan_erkan_dictionary_1-2.0.0.dist-info/RECORD
