Metadata-Version: 2.1
Name: kamil-kaan-erkan-dictionary-1
Version: 2.0.0
Summary: UNKNOWN
Author: Kamil Kaan Erkan
License: UNKNOWN
Platform: UNKNOWN
Requires-Python: >=3.8
Requires-Dist: requests (>=2.23.0)
